setup.py
distribution_basics/Binomialdistribution.py
distribution_basics/Gaussiandistribution.py
distribution_basics/Generaldistribution.py
distribution_basics/__init__.py
distribution_basics.egg-info/PKG-INFO
distribution_basics.egg-info/SOURCES.txt
distribution_basics.egg-info/dependency_links.txt
distribution_basics.egg-info/not-zip-safe
distribution_basics.egg-info/top_level.txt